<Manifest ClientNode="100" Node="123">
	<DestFolder Name="c:\Program Files\Radiant\FastPoint\Bin">
		<File FileSize="13824" ID="1654" Name="Agent_AlertInterface.dll" RebootRequired="true" SourcePath="c:\program files\radiant\VIR\Bin\NT-x86" Time="2016-12-15 18:16:26" />
		<File FileSize="80384" ID="1617" Name="ApexClasses.dll" RebootRequired="true" SourcePath="c:\program files\radiant\VIR\Bin\NT-x86" Time="2016-12-15 18:16:14" />
		<File FileSize="14336" ID="9002" Name="ChangeServerClient.dll" RebootRequired="true" SourcePath="c:\program files\radiant\VIR\Bin\NT-x86" Time="2016-12-15 18:16:30" />
		<File FileSize="13824" ID="10090" Name="ChangeServerServer.dll" RebootRequired="true" SourcePath="c:\program files\radiant\VIR\Bin\NT-x86" Time="2016-12-15 18:16:32" />
		<File FileSize="41984" ID="7775" Name="Device_GsmInterface.dll" RebootRequired="true" SourcePath="c:\program files\radiant\VIR\Bin\NT-x86" Time="2016-12-15 18:16:22" />
		<File FileSize="112128" ID="2011" Name="DeviceBaseClasses.dll" RebootRequired="true" SourcePath="c:\program files\radiant\VIR\Bin\NT-x86" Time="2016-11-30 10:51:38" />
		<File FileSize="70656" ID="1001" Name="DevMan.exe" RebootRequired="true" SourcePath="c:\program files\radiant\VIR\Bin\NT-x86" Time="2016-11-30 10:51:42" />
		<File FileSize="330040" ID="7849" Name="DiagExtension.dll" RebootRequired="true" SourcePath="c:\program files\radiant\VIR\Bin\NT-x86" Time="2014-09-02 20:18:36" />
		<File FileSize="120832" ID="1615" Name="Dispenser_FuelInterface.dll" RebootRequired="true" SourcePath="c:\program files\radiant\VIR\Bin\NT-x86" Time="2016-12-15 18:17:00" />
		<File FileSize="31232" ID="10012" Name="Dispenser_ICRInterface.dll" RebootRequired="true" SourcePath="c:\program files\radiant\VIR\Bin\NT-x86" Time="2016-12-15 18:16:42" />
		<File FileSize="1349568" ID="10122" Name="EpsilonGCMPlugin.dll" RebootRequired="true" SourcePath="c:\program files\radiant\VIR\Bin\NT-x86" Time="2016-10-26 20:45:56" />
		<File FileSize="387384" ID="7850" Name="FileExtension.dll" RebootRequired="true" SourcePath="c:\program files\radiant\VIR\Bin\NT-x86" Time="2014-09-02 20:18:40" />
		<File FileSize="84480" ID="9001" Name="ForecourtInterface.dll" RebootRequired="true" SourcePath="c:\program files\radiant\VIR\Bin\NT-x86" Time="2016-12-15 18:16:24" />
		<File FileSize="223744" ID="10019" Name="Fuel_Base.dll" RebootRequired="true" SourcePath="c:\program files\radiant\VIR\Bin\NT-x86" Time="2016-12-15 18:17:26" />
		<File FileSize="75776" ID="10024" Name="Fuel_Wayne.dll" RebootRequired="true" SourcePath="c:\program files\radiant\VIR\Bin\NT-x86" Time="2016-12-15 18:17:36" />
		<File FileSize="75776" ID="10024" Name="Fuel_Gilbarco.dll" RebootRequired="true" SourcePath="c:\program files\radiant\VIR\Bin\NT-x86" Time="2016-12-30 18:17:36" />        
		<File FileSize="504320" ID="2006" Name="FuelPumps.dll" RebootRequired="true" SourcePath="c:\program files\radiant\VIR\Bin\NT-x86" Time="2016-12-15 18:59:38" />
		<File FileSize="35840" ID="7759" Name="HTTPClient.dll" RebootRequired="true" SourcePath="c:\program files\radiant\VIR\Bin\NT-x86" Time="2016-11-30 10:52:52" />
		<File FileSize="3063296" ID="10030" Name="Icarus.exe" RebootRequired="true" SourcePath="c:\program files\radiant\VIR\Bin\NT-x86" Time="2016-12-15 18:17:58" />
		<File FileSize="696320" ID="9079" Name="Linq3.dll" RebootRequired="true" SourcePath="c:\program files\radiant\VIR\Bin\NT-x86" Time="2016-12-15 18:17:58" />
		<File FileSize="35840" ID="5631" Name="IcarusStatusClient.dll" RebootRequired="true" SourcePath="c:\program files\radiant\VIR\Bin\NT-x86" Time="2016-12-15 18:16:34" />
		<File FileSize="25088" ID="10034" Name="IcarusStatusServer.dll" RebootRequired="true" SourcePath="c:\program files\radiant\VIR\Bin\NT-x86" Time="2016-12-15 18:16:34" />
		<File FileSize="173568" ID="10035" Name="ICR_Base.dll" RebootRequired="true" SourcePath="c:\program files\radiant\VIR\Bin\NT-x86" Time="2016-12-15 18:16:54" />
		<File FileSize="169472" Name="ICR_Wayne.dll" Time="2017-12-06 17:07:10" SourcePath="c:\program files\radiant\VIR\Bin\NT-x86" RebootRequired="true" ID="10038"></File>
		<File FileSize="1191936" ID="10184" Name="ICR_Gilbarco.dll" RebootRequired="true" SourcePath="c:\program files\radiant\VIR\Bin\NT-x86" Time="2016-12-30 13:17:40" />
		<File FileSize="1191936" ID="10184" Name="ICR_Generic.dll" RebootRequired="true" SourcePath="c:\program files\radiant\VIR\Bin\NT-x86" Time="2016-12-29 13:17:40" />
		<File FileSize="1191936" ID="10184" Name="ICR_GilbarcoSPOT_US.dll" RebootRequired="true" SourcePath="c:\program files\radiant\VIR\Bin\NT-x86" Time="2016-12-29 13:17:40" />
		<File FileSize="1191936" ID="10184" Name="ICR_WayneIXCAT.dll" RebootRequired="true" SourcePath="c:\program files\radiant\VIR\Bin\NT-x86" Time="2016-12-29 13:17:40" />
		<File FileSize="118272" ID="8076" Name="IFSF_Controller.dll" RebootRequired="true" SourcePath="c:\program files\radiant\VIR\Bin\NT-x86" Time="2013-05-02 10:45:52" />
		<File FileSize="179200" ID="10042" Name="JagEventManager.exe" RebootRequired="true" SourcePath="c:\program files\radiant\VIR\Bin\NT-x86" Time="2016-12-15 18:16:14" />
		<File FileSize="29696" ID="10088" Name="JagLoggerPlugin.dll" RebootRequired="true" SourcePath="c:\program files\radiant\VIR\Bin\NT-x86" Time="2016-12-15 18:16:24" />
		<File FileSize="123392" ID="2016" Name="Jagports.dll" RebootRequired="true" SourcePath="c:\program files\radiant\VIR\Bin\NT-x86" Time="2016-12-15 18:16:12" />
		<File FileSize="23040" ID="10116" Name="JagSigmaClient.dll" RebootRequired="true" SourcePath="c:\program files\radiant\VIR\Bin\NT-x86" Time="2016-12-15 18:16:12" />
		<File FileSize="1123840" ID="9065" Name="libeay32.dll" RebootRequired="true" SourcePath="c:\program files\radiant\VIR\Bin\NT-x86" Time="2016-09-27 03:01:50" />
		<File FileSize="61952" ID="9041" Name="LocalQueue.dll" RebootRequired="true" SourcePath="c:\program files\radiant\VIR\Bin\NT-x86" Time="2016-11-30 10:53:04" />
		<File Name="mosquitto.dll" Time="2021-11-22 01:09:40" FileSize="71168" SourcePath="c:\program files\radiant\VIR\Bin\NT-x86" RebootRequired="true" ID="9185"></File>
		<File FileSize="84992" ID="7760" Name="MiniZip.dll" RebootRequired="true" SourcePath="c:\program files\radiant\VIR\Bin\NT-x86" Time="2016-11-30 10:50:16" />
		<File FileSize="616960" ID="9021" Name="MRDGCMPlugin.dll" RebootRequired="true" SourcePath="c:\program files\radiant\VIR\Bin\NT-x86" Time="2016-12-15 19:03:04" />
		<File FileSize="13312" Name="POS_AlertInterface.dll" Time="2017-12-06 17:05:46" SourcePath="c:\program files\radiant\VIR\Bin\NT-x86" RebootRequired="true" ID="1653"></File>
		<File FileSize="14848" ID="1650" Name="POS_CarwashInterface.dll" RebootRequired="true" SourcePath="c:\program files\radiant\VIR\Bin\NT-x86" Time="2016-12-15 18:16:38" />
		<File FileSize="93696" ID="1616" Name="POS_FuelInterface.dll" RebootRequired="true" SourcePath="c:\program files\radiant\VIR\Bin\NT-x86" Time="2016-12-15 18:16:44" />
		<File FileSize="52736" ID="10057" Name="POS_GsmInterface.dll" RebootRequired="true" SourcePath="c:\program files\radiant\VIR\Bin\NT-x86" Time="2016-12-15 18:16:24" />
		<File FileSize="49664" ID="1623" Name="POS_ICRInterface.dll" RebootRequired="true" SourcePath="c:\program files\radiant\VIR\Bin\NT-x86" Time="2016-12-15 18:16:36" />
		<File FileSize="13312" ID="1656" Name="POS_PriceSignInterface.dll" RebootRequired="true" SourcePath="c:\program files\radiant\VIR\Bin\NT-x86" Time="2016-12-15 18:16:40" />
		<File FileSize="465622" ID="9057" Name="Prerequisites.exe" RebootRequired="true" SourcePath="c:\program files\radiant\VIR\Bin\NT-x86" Time="2016-12-15 19:22:26" />
		<File FileSize="104960" ID="9046" Name="PriceChangeManager.exe" RebootRequired="true" SourcePath="c:\program files\radiant\VIR\Bin\NT-x86" Time="2016-12-15 18:17:18" />
		<File FileSize="1179072" ID="9019" Name="RadGCM.dll" RebootRequired="true" SourcePath="c:\program files\radiant\VIR\Bin\NT-x86" Time="2016-10-26 20:45:54" />
		<File FileSize="28672" ID="1024" Name="RadiantTaskKill.exe" RebootRequired="true" SourcePath="c:\program files\radiant\VIR\Bin\NT-x86" Time="2016-11-30 10:48:16" />
		<File FileSize="33792" ID="7761" Name="RadioDiagnostics.dll" RebootRequired="true" SourcePath="c:\program files\radiant\VIR\Bin\NT-x86" Time="2016-11-30 10:54:56" />
		<File FileSize="41984" ID="9042" Name="RadioProxy.dll" RebootRequired="true" SourcePath="c:\program files\radiant\VIR\Bin\NT-x86" Time="2016-11-30 10:48:44" />
		<File FileSize="77312" ID="1612" Name="RadPipeClient.dll" RebootRequired="true" SourcePath="c:\program files\radiant\VIR\Bin\NT-x86" Time="2016-11-30 10:50:12" />
		<File FileSize="100864" ID="1603" Name="RadRam.dll" RebootRequired="true" SourcePath="c:\program files\radiant\VIR\Bin\NT-x86" Time="2016-11-30 10:50:40" />
		<File FileSize="88576" ID="9040" Name="RadRamBlobQueue.dll" RebootRequired="true" SourcePath="c:\program files\radiant\VIR\Bin\NT-x86" Time="2016-11-30 10:51:30" />
		<File FileSize="739328" ID="7854" Name="RadStart.exe" RebootRequired="true" SourcePath="c:\program files\radiant\VIR\Bin\NT-x86" Time="2016-11-30 10:58:12" />
		<File FileSize="290304" ID="1614" Name="RadUtilities.dll" RebootRequired="true" SourcePath="c:\program files\radiant\VIR\Bin\NT-x86" Time="2016-11-30 10:50:06" />
		<File FileSize="8704" ID="9078" Name="RadxOsalStrings.dll" RebootRequired="true" SourcePath="c:\program files\radiant\VIR\Bin\NT-x86" Time="2016-08-22 20:23:08" />
		<File FileSize="25088" ID="9075" Name="radxstrings.dll" RebootRequired="true" SourcePath="c:\program files\radiant\VIR\Bin\NT-x86" Time="2016-08-22 20:23:12" />
		<File FileSize="194048" ID="9076" Name="radxvalues.dll" RebootRequired="true" SourcePath="c:\program files\radiant\VIR\Bin\NT-x86" Time="2016-08-22 20:23:20" />
		<File FileSize="47616" ID="9077" Name="radxxml.dll" RebootRequired="true" SourcePath="c:\program files\radiant\VIR\Bin\NT-x86" Time="2016-08-22 20:23:14" />
		<File FileSize="280376" ID="9056" Name="RemoteLogExtension.dll" RebootRequired="true" SourcePath="c:\program files\radiant\VIR\Bin\NT-x86" Time="2014-09-02 20:19:40" />
		<File FileSize="961" ID="1021" Name="RestartComponents.bat" RebootRequired="true" SourcePath="c:\program files\radiant\VIR\Bin\NT-x86" Time="2016-11-30 10:48:08" />
		<File FileSize="181560" ID="9069" Name="RS_SSLLocks.dll" RebootRequired="true" SourcePath="c:\program files\radiant\VIR\Bin\NT-x86" Time="2014-08-25 14:33:42" />
		<File FileSize="860984" ID="9070" Name="RSNVP.dll" RebootRequired="true" SourcePath="c:\program files\radiant\VIR\Bin\NT-x86" Time="2014-08-25 14:24:22" />
		<File FileSize="1139136" ID="10016" Name="RSNVPRPOS.dll" RebootRequired="true" SourcePath="c:\program files\radiant\VIR\Bin\NT-x86" Time="2016-10-26 20:37:46" />
		<File FileSize="2241" ID="1023" Name="RunInWindowStyle.js" RebootRequired="true" SourcePath="c:\program files\radiant\VIR\Bin\NT-x86" Time="2016-11-30 10:48:08" />
		<File FileSize="854840" ID="1019" Name="SerialLink.exe" RebootRequired="true" SourcePath="c:\program files\radiant\VIR\Bin\NT-x86" Time="2014-09-02 20:19:26" />
		<File FileSize="1418240" ID="9017" Name="SigmaAPI.dll" RebootRequired="true" SourcePath="c:\program files\radiant\VIR\Bin\NT-x86" Time="2016-10-26 14:47:14" />
		<File FileSize="1194432" ID="9023" Name="SigmaGCMPlugIn.dll" RebootRequired="true" SourcePath="c:\program files\radiant\VIR\Bin\NT-x86" Time="2016-10-26 20:45:56" />
		<File FileSize="306176" ID="1008" Name="SMClient.exe" RebootRequired="true" SourcePath="c:\program files\radiant\VIR\Bin\NT-x86" Time="2016-11-30 10:55:54" />
		<File FileSize="898560" ID="1602" Name="SMServices.dll" RebootRequired="true" SourcePath="c:\program files\radiant\VIR\Bin\NT-x86" Time="2016-11-30 10:50:56" />
		<File FileSize="54784" ID="7916" Name="SoapClient.dll" RebootRequired="true" SourcePath="c:\program files\radiant\VIR\Bin\NT-x86" Time="2016-11-30 10:56:10" />
		<File FileSize="266752" ID="9066" Name="ssleay32.dll" RebootRequired="true" SourcePath="c:\program files\radiant\VIR\Bin\NT-x86" Time="2016-09-27 03:01:50" />
		<File FileSize="691200" ID="9084" Name="StdLogger.dll" RebootRequired="true" SourcePath="c:\program files\radiant\VIR\Bin\NT-x86" Time="2016-11-30 10:52:44" />
		<File FileSize="393728" ID="1004" Name="TeleQ.exe" RebootRequired="true" SourcePath="c:\program files\radiant\VIR\Bin\NT-x86" Time="2016-11-30 10:54:08" />
		<File FileSize="44544" ID="2012" Name="XMLParse.dll" RebootRequired="true" SourcePath="c:\program files\radiant\VIR\Bin\NT-x86" Time="2016-11-30 10:48:52" />
	</DestFolder>
	<DestFolder Name="c:\Program Files\Radiant\FastPoint">
		<File FileSize="858" ID="2600" Name="autoexec.two" RebootRequired="true" SourcePath="c:\program files\radiant\lighthouse\data\relaygen" Time="2016-12-15 18:45:26" />
		<File FileSize="754" ID="2613" Name="ControlPanel.cer" RebootRequired="true" SourcePath="c:\program files\radiant\lighthouse\data\relaygen" Time="2016-12-15 18:45:26" />
		<File FileSize="134" ID="2605" Name="Epsilon.cer" RebootRequired="true" SourcePath="c:\program files\radiant\lighthouse\data\relaygen" Time="2016-12-22 15:50:30" />
		<File FileSize="659" ID="10087" Name="JagDefault.cer" RebootRequired="true" SourcePath="c:\program files\radiant\lighthouse\data\relaygen" Time="2016-12-15 18:07:30" />
		<File FileSize="234" ID="9022" Name="MRD.cer" RebootRequired="true" SourcePath="c:\program files\radiant\lighthouse\data\relaygen" Time="2016-12-15 18:45:26" />
		<File FileSize="410" ID="9020" Name="RadGCM.cer" RebootRequired="true" SourcePath="c:\program files\radiant\lighthouse\data\relaygen" Time="2016-07-22 21:14:20" />
		<File FileSize="325" ID="2612" Name="RadPipe.cer" RebootRequired="true" SourcePath="c:\program files\radiant\lighthouse\data\relaygen" Time="2016-12-15 18:45:26" />
		<File FileSize="7773" ID="7858" Name="RadStart.ini" RebootRequired="true" SourcePath="c:\program files\radiant\lighthouse\data\relaygen" Time="2016-12-15 18:45:26" />
		<File FileSize="1427" ID="2607" Name="SerialLink.cer" RebootRequired="true" SourcePath="c:\program files\radiant\lighthouse\data\relaygen" Time="2014-06-13 15:02:18" />
	</DestFolder>
	<DestFolder Name="c:\Program Files\Radiant\FastPoint\Data">
		<File FileSize="2412" ID="8160" Name="Card.dat" RebootRequired="true" SourcePath="c:\program files\radiant\lighthouse\data\relaygen" Time="2016-12-22 15:55:35" />
		<File FileSize="3052" ID="119" Name="DevSet.dat" RebootRequired="true" SourcePath="c:\program files\radiant\lighthouse\data\relaygen" Time="2017-01-06 19:42:40" />
		<File FileSize="812" ID="130" Name="Fuel_Dispenser.dat" RebootRequired="false" SourcePath="c:\program files\radiant\lighthouse\data\relaygen" Time="2016-12-22 15:55:22" />
		<File FileSize="1356" ID="129" Name="Fuel_SiteInfo.dat" RebootRequired="false" SourcePath="c:\program files\radiant\lighthouse\data\relaygen" Time="2016-12-22 15:55:21" />
		<File FileSize="68253" ID="10031" Name="IcarusConfig.xml" RebootRequired="false" SourcePath="c:\program files\radiant\lighthouse\data\relaygen" Time="2017-01-11 20:42:06" />
		<File FileSize="11423" ID="10032" Name="IcarusDCs.xml" RebootRequired="true" SourcePath="c:\program files\radiant\lighthouse\data\relaygen" Time="2013-03-12 15:05:35" />
		<File FileSize="303094" ID="10033" Name="IcarusItems.xml" RebootRequired="true" SourcePath="c:\program files\radiant\lighthouse\data\relaygen" Time="2016-12-22 15:55:26" />
		<File FileSize="1395" ID="7833" Name="LHVERSIONINFO.txt" RebootRequired="true" SourcePath="c:\program files\radiant\lighthouse\data\relaygen" Time="2016-12-22 15:52:18" />
		<File FileSize="100" ID="10054" Name="Pay_Point.dat" RebootRequired="true" SourcePath="c:\program files\radiant\lighthouse\data\relaygen" Time="2017-01-06 19:42:18" />
		<File FileSize="29156" ID="116" Name="PrintFormat.dat" RebootRequired="true" SourcePath="c:\program files\radiant\lighthouse\data\relaygen\Terminal100" Time="2017-01-06 19:42:38" />
		<File FileSize="660" ID="115" Name="PrintRoute.dat" RebootRequired="true" SourcePath="c:\program files\radiant\lighthouse\data\relaygen" Time="2017-01-06 19:42:41" />
		<File FileSize="7340" ID="133" Name="SMClient.dat" RebootRequired="true" SourcePath="c:\program files\radiant\lighthouse\data\relaygen" Time="2017-01-06 19:42:40" />
		<File FileSize="149" ID="7863" Name="SOAPConfigLocation.xml" RebootRequired="true" SourcePath="c:\program files\radiant\lighthouse\data\relaygen" Time="2016-12-22 15:50:30" />
		<File FileSize="128718" ID="10134" Name="TerminalCommands.xsd" RebootRequired="true" SourcePath="c:\program files\radiant\lighthouse\data\relaygen" Time="2016-12-15 18:07:30" />
		<File FileSize="4860" ID="10135" Name="CTLS_Capk_MSD.txt" RebootRequired="true" SourcePath="c:\program files\radiant\lighthouse\data\relaygen" Time="2019-7-11 2:10:30" />
		<File FileSize="4860" ID="10136" Name="CTLS_Config_MSD.txt" RebootRequired="true" SourcePath="c:\program files\radiant\lighthouse\data\relaygen" Time="2019-7-11 2:10:30" />
		<File FileSize="1865" ID="10137" Name="M5_EMVScreen.bin" RebootRequired="true" SourcePath="c:\program files\radiant\lighthouse\data\relaygen" Time="2019-7-11 2:10:30" />
		<File FileSize="895" ID="10138" Name="M5_MsgEmv.bin" RebootRequired="true" SourcePath="c:\program files\radiant\lighthouse\data\relaygen" Time="2019-7-11 2:10:30" />
		<File FileSize="895" ID="10139" Name="M5_MsgEmv_NoBypass.bin" RebootRequired="true" SourcePath="c:\program files\radiant\lighthouse\data\relaygen" Time="2019-7-11 2:10:30" />
		<File FileSize="3695" ID="10140" Name="M5_SPOTEMVMessageFileEN.bin" RebootRequired="true" SourcePath="c:\program files\radiant\lighthouse\data\relaygen" Time="2019-7-11 2:10:30" />
		<File FileSize="3695" ID="10141" Name="M5_SPOTEMVMessageFileFR.bin" RebootRequired="true" SourcePath="c:\program files\radiant\lighthouse\data\relaygen" Time="2019-7-11 2:10:30" />
		<File FileSize="1865" ID="10142" Name="M5_SPOTInjectedNonPinPrompts.bin" RebootRequired="true" SourcePath="c:\program files\radiant\lighthouse\data\relaygen" Time="2019-7-11 2:10:30" />
		<File FileSize="895" ID="10143" Name="M5_SPOTInjectedPinPrompts.bin" RebootRequired="true" SourcePath="c:\program files\radiant\lighthouse\data\relaygen" Time="2019-7-11 2:10:30" />
		<File FileSize="1895" ID="10144" Name="M5_SPOTNonPinDefaultTemplate.bin" RebootRequired="true" SourcePath="c:\program files\radiant\lighthouse\data\relaygen" Time="2019-7-11 2:10:30" />
		<File FileSize="1895" ID="10145" Name="M5_SPOTPinDefaultTemplate.bin" RebootRequired="true" SourcePath="c:\program files\radiant\lighthouse\data\relaygen" Time="2019-7-11 2:10:30" />
		<File FileSize="3695" ID="10146" Name="M7_EMVMessagesEN.bin" RebootRequired="true" SourcePath="c:\program files\radiant\lighthouse\data\relaygen" Time="2019-7-11 2:10:30" />
		<File FileSize="3695" ID="10147" Name="M7_EMVMessagesFR.bin" RebootRequired="true" SourcePath="c:\program files\radiant\lighthouse\data\relaygen" Time="2019-7-11 2:10:30" />
		<File FileSize="2919" ID="10148" Name="M7_EMVMessagesPin.bin" RebootRequired="true" SourcePath="c:\program files\radiant\lighthouse\data\relaygen" Time="2019-7-11 2:10:30" />
		<File FileSize="2919" ID="10149" Name="M7_EMVMessagesPin.bin_NoBypass_US_Canada" RebootRequired="true" SourcePath="c:\program files\radiant\lighthouse\data\relaygen" Time="2019-7-11 2:10:30" />
		<File FileSize="2919" ID="10150" Name="M7_EMVMessagesPin.bin_PinBypass_US" RebootRequired="true" SourcePath="c:\program files\radiant\lighthouse\data\relaygen" Time="2019-7-11 2:10:30" />
		<File FileSize="2919" ID="10151" Name="M7_EMVMessagesPin_NoBypass_US_Canada.bin" RebootRequired="true" SourcePath="c:\program files\radiant\lighthouse\data\relaygen" Time="2019-7-11 2:10:30" />
		<File FileSize="4163" ID="10152" Name="M7_EMVScreen.bin" RebootRequired="true" SourcePath="c:\program files\radiant\lighthouse\data\relaygen" Time="2019-7-11 2:10:30" />
		<File FileSize="3392" ID="10153" Name="M7_SPOTInjectedNonPinPrompts.bin" RebootRequired="true" SourcePath="c:\program files\radiant\lighthouse\data\relaygen" Time="2019-7-11 2:10:30" />
		<File FileSize="2919" ID="10154" Name="M7_SPOTInjectedPinPrompts.bin" RebootRequired="true" SourcePath="c:\program files\radiant\lighthouse\data\relaygen" Time="2019-7-11 2:10:30" />
		<File FileSize="3392" ID="10155" Name="M7_SPOTNonPinDefaultTemplate.bin" RebootRequired="true" SourcePath="c:\program files\radiant\lighthouse\data\relaygen" Time="2019-7-11 2:10:30" />
		<File FileSize="3392" ID="10156" Name="M7_SPOTPinDefaultTemplate.bin" RebootRequired="true" SourcePath="c:\program files\radiant\lighthouse\data\relaygen" Time="2019-7-11 2:10:30" />
		<File FileSize="895" ID="10157" Name="SPOT_UIOverride.txt" RebootRequired="true" SourcePath="c:\program files\radiant\lighthouse\data\relaygen" Time="2019-7-11 2:10:30" />
		<File FileSize="895" ID="10158" Name="SPOTEMVDefaultTemplate.TMP" RebootRequired="true" SourcePath="c:\program files\radiant\lighthouse\data\relaygen" Time="2019-7-11 2:10:30" />
		<File FileSize="32777" ID="10159" Name="SPOTEMVDefaultTemplate.TMP.lic" RebootRequired="true" SourcePath="c:\program files\radiant\lighthouse\data\relaygen" Time="2019-7-11 2:10:30" />
		<File FileSize="671753" ID="10160" Name="SPOTEMVDefaultTemplate.TMP.lic0" RebootRequired="true" SourcePath="c:\program files\radiant\lighthouse\data\relaygen" Time="2019-7-11 2:10:30" />
		<File FileSize="3607" ID="10161" Name="SPOTEMVMessageFileEN.txt" RebootRequired="true" SourcePath="c:\program files\radiant\lighthouse\data\relaygen" Time="2019-7-11 2:10:30" />
		<File FileSize="3607" ID="10162" Name="SPOTEMVMessageFileFR.txt" RebootRequired="true" SourcePath="c:\program files\radiant\lighthouse\data\relaygen" Time="2019-7-11 2:10:30" />
		<File FileSize="895" ID="10163" Name="SPOTEMVmessageFilePIN.txt" RebootRequired="true" SourcePath="c:\program files\radiant\lighthouse\data\relaygen" Time="2019-7-11 2:10:30" />
		<File FileSize="32777" ID="10164" Name="SPOTEMVmessageFilePIN.txt.lic" RebootRequired="true" SourcePath="c:\program files\radiant\lighthouse\data\relaygen" Time="2019-7-11 2:10:30" />
		<File FileSize="671753" ID="10165" Name="SPOTEMVmessageFilePIN.txt.lic0" RebootRequired="true" SourcePath="c:\program files\radiant\lighthouse\data\relaygen" Time="2019-7-11 2:10:30" />
		<File FileSize="895" ID="10166" Name="SPOTInjectedNonPinPrompts.TXT" RebootRequired="true" SourcePath="c:\program files\radiant\lighthouse\data\relaygen" Time="2019-7-11 2:10:30" />
		<File FileSize="32777" ID="10167" Name="SPOTInjectedNonPinPrompts.TXT.lic" RebootRequired="true" SourcePath="c:\program files\radiant\lighthouse\data\relaygen" Time="2019-7-11 2:10:30" />
		<File FileSize="671753" ID="10168" Name="SPOTInjectedNonPinPrompts.TXT.lic0" RebootRequired="true" SourcePath="c:\program files\radiant\lighthouse\data\relaygen" Time="2019-7-11 2:10:30" />
		<File FileSize="895" ID="10169" Name="SPOTInjectedPinPrompts.TXT" RebootRequired="true" SourcePath="c:\program files\radiant\lighthouse\data\relaygen" Time="2019-7-11 2:10:30" />
		<File FileSize="32777" ID="10170" Name="SPOTInjectedPinPrompts.TXT.lic" RebootRequired="true" SourcePath="c:\program files\radiant\lighthouse\data\relaygen" Time="2019-7-11 2:10:30" />
		<File FileSize="671750" ID="10171" Name="SPOTInjectedPinPrompts.TXT.lic0" RebootRequired="true" SourcePath="c:\program files\radiant\lighthouse\data\relaygen" Time="2019-7-11 2:10:30" />
		<File FileSize="895" ID="10172" Name="SPOTNonPinDefaultTemplate.TMP" RebootRequired="true" SourcePath="c:\program files\radiant\lighthouse\data\relaygen" Time="2019-7-11 2:10:30" />
		<File FileSize="32777" ID="10173" Name="SPOTNonPinDefaultTemplate.TMP.lic" RebootRequired="true" SourcePath="c:\program files\radiant\lighthouse\data\relaygen" Time="2019-7-11 2:10:30" />
		<File FileSize="671750" ID="10174" Name="SPOTNonPinDefaultTemplate.TMP.lic0" RebootRequired="true" SourcePath="c:\program files\radiant\lighthouse\data\relaygen" Time="2019-7-11 2:10:30" />
		<File FileSize="895" ID="10175" Name="SPOTPinDefaultTemplate.TMP" RebootRequired="true" SourcePath="c:\program files\radiant\lighthouse\data\relaygen" Time="2019-7-11 2:10:30" />
		<File FileSize="32777" ID="10176" Name="SPOTPinDefaultTemplate.TMP.lic" RebootRequired="true" SourcePath="c:\program files\radiant\lighthouse\data\relaygen" Time="2019-7-11 2:10:30" />
		<File FileSize="671750" ID="10177" Name="SPOTPinDefaultTemplate.TMP.lic0" RebootRequired="true" SourcePath="c:\program files\radiant\lighthouse\data\relaygen" Time="2019-7-11 2:10:30" />
	</DestFolder>
</Manifest>
